Metadata-Version: 2.1
Name: EGL-ML-CHALLENGE
Version: 0.1.0
Summary: Useful stuff
Home-page: http://pypi.python.org/pypi/MyApplication_v010/
Author: Abi
Author-email: aforabhishek@hotmail.com
License: UNKNOWN
Platform: UNKNOWN
